mercator_logger/__init__.py
mercator_logger/main.py
mercator_logger-0.1.0.dist-info/METADATA
mercator_logger-0.1.0.dist-info/WHEEL
mercator_logger-0.1.0.dist-info/top_level.txt
mercator_logger-0.1.0.dist-info/RECORD
